hostingde/__init__.py
hostingde/__version__.py
hostingde/api.py
hostingde/client.py
hostingde/exceptions.py
hostingde/hostingde.py
hostingde/job_waiter.py
hostingde/paginator.py
hostingde/session.py
hostingde/account/__init__.py
hostingde/account/account.py
hostingde/account/requests/__init__.py
hostingde/billing/__init__.py
hostingde/billing/billing.py
hostingde/dns/__init__.py
hostingde/dns/dns.py
hostingde/dns/requests/__init__.py
hostingde/dns/requests/create_new_zone.py
hostingde/dns/requests/delete_zone.py
hostingde/dns/requests/update_records_request.py
hostingde/dns/requests/update_zone_request.py
hostingde/domain/__init__.py
hostingde/domain/domain.py
hostingde/domain/requests/__init__.py
hostingde/domain/requests/check_availability.py
hostingde/domain/requests/register_domain.py
hostingde/model/__init__.py
hostingde/model/account.py
hostingde/model/billing.py
hostingde/model/domain.py
hostingde/model/domain_contact.py
hostingde/model/filter.py
hostingde/model/job.py
hostingde/model/record.py
hostingde/model/soa_values.py
hostingde/model/sort.py
hostingde/model/ssl.py
hostingde/model/zone.py
hostingde/model/zone_config.py
hostingde/ssl/__init__.py
hostingde/ssl/ssl.py
python_hostingde-0.9.1.dist-info/LICENSE
python_hostingde-0.9.1.dist-info/METADATA
python_hostingde-0.9.1.dist-info/WHEEL
python_hostingde-0.9.1.dist-info/top_level.txt
python_hostingde-0.9.1.dist-info/RECORD
