Metadata-Version: 2.1
Name: python-hostingde
Version: 0.9.1
Summary: Interact with HostingDe API
Home-page: https://github.com/cancom/python-hostingde
Author: CANCOM OpenSource
Author-email: opensource@cancom.de
License: MIT
Project-URL: Source, https://github.com/cancom/python-hostingde
Project-URL: Bug Reports, https://github.com/cancom/python-hostingde/issues
Classifier: Intended Audience :: Developers
Classifier: License :: OSI Approved :: MIT License
Classifier: Natural Language :: English
Classifier: Operating System :: POSIX
Classifier: Operating System :: Microsoft :: Windows
Classifier: Programming Language :: Python
Classifier: Programming Language :: Python :: 3
Classifier: Programming Language :: Python :: 3.6
Classifier: Programming Language :: Python :: 3.7
Classifier: Programming Language :: Python :: 3.8
Classifier: Programming Language :: Python :: 3.9
Classifier: Programming Language :: Python :: 3.10
Requires-Python: >=3.6.0
License-File: LICENSE
Requires-Dist: requests (>=2.25.1)
Requires-Dist: marshmallow (==3.10.0)
Requires-Dist: marshmallow-dataclass (==8.3.1)
Requires-Dist: marshmallow-enum (==1.5.1)
Requires-Dist: urllib3 (~=1.26.3)
